academic_markdown/__init__.py
academic_markdown/academic_markdown.py
scripts/build_docker.sh
scripts/check_health.sh
scripts/install_tectonic.sh
academic_markdown-0.2.8.dist-info/METADATA
academic_markdown-0.2.8.dist-info/WHEEL
academic_markdown-0.2.8.dist-info/entry_points.txt
academic_markdown-0.2.8.dist-info/top_level.txt
academic_markdown-0.2.8.dist-info/RECORD
