Metadata-Version: 2.1
Name: academic_markdown
Version: 0.2.8
Summary: CLI for converting Markdown to Latex using pandoc and Docker.
Author-email: Zohar Cochavi <cochavi.zohar@protonmail.com>
Project-URL: Homepage, https://github.com/cochaviz/academic_markdown_cli
Project-URL: Bug Tracker, https://github.com/cochaviz/academic_markdown_cli/issues
Classifier: Programming Language :: Python :: 3
Classifier: License :: OSI Approved :: MIT License
Classifier: Operating System :: OS Independent
Requires-Python: >=3.7
Requires-Dist: typer[all]
Requires-Dist: pyyaml
Requires-Dist: python-frontmatter
